csv_comparison_tool/__init__.py
csv_comparison_tool/compare.py
csv_comparison_tool-0.1.dist-info/METADATA
csv_comparison_tool-0.1.dist-info/WHEEL
csv_comparison_tool-0.1.dist-info/entry_points.txt
csv_comparison_tool-0.1.dist-info/top_level.txt
csv_comparison_tool-0.1.dist-info/RECORD
